README.md
setup.py
toolbox_dir.egg-info/PKG-INFO
toolbox_dir.egg-info/SOURCES.txt
toolbox_dir.egg-info/dependency_links.txt
toolbox_dir.egg-info/entry_points.txt
toolbox_dir.egg-info/requires.txt
toolbox_dir.egg-info/top_level.txt
toolboxdir/__init__.py
toolboxdir/toolboxdir.py
toolboxdir/version.py