Metadata-Version: 2.1
Name: toolbox-dir
Version: 0.0.1
Summary: Shortcut tool for Toolbox (https://containertoolbx.org/) that can associated diretories with a toolbox.
Home-page: https://github.com/bostrt/toolbox-dir
Author: bostrt
